<?xml version="1.0" encoding="UTF-8"?>
<con:soapui-project id="1dbe474f-0702-4a16-bca6-0793bd009254" activeEnvironment="Default" name="testsoap" resourceRoot="${projectDir}" soapui-version="5.8.0"
  xmlns:con="http://eviware.com/soapui/config">
  <con:settings/>
  <con:interface xsi:type="con:WsdlInterface" id="e669f201-2cc6-4f15-9b5a-51629cdac8d3" wsaVersion="NONE" name="CalculatorSoap12" type="wsdl" bindingName="{http://tempuri.org/}CalculatorSoap12" soapVersion="1_2" anonymous="optional" definition="http://www.dneonline.com/calculator.asmx?WSDL"
    xmlns:xsi="http://www.w3.org/2001/XMLSchema-instance">
    <con:settings/>
    <con:definitionCache/>
    <con:endpoints>
      <con:endpoint>http://www.dneonline.com/calculator.asmx</con:endpoint>
    </con:endpoints>
    <con:operation id="a607556d-fe10-423e-928e-57f4a318c15a" isOneWay="false" action="http://tempuri.org/Add" name="Add" bindingOperationName="Add" type="Request-Response" inputName="" receivesAttachments="false" sendsAttachments="false" anonymous="optional">
      <con:settings/>
      <con:call id="3c3e4c00-44a0-4a34-975d-f99072583005" name="Request 1">
        <con:settings>
          <con:setting id="com.eviware.soapui.impl.wsdl.WsdlRequest@request-headers">&lt;xml-fragment/></con:setting>
        </con:settings>
        <con:encoding>UTF-8</con:encoding>
        <con:endpoint>http://www.dneonline.com/calculator.asmx</con:endpoint>
        <con:request><![CDATA[<soap:Envelope xmlns:soap="http://www.w3.org/2003/05/soap-envelope" xmlns:tem="http://tempuri.org/">
   <soap:Header/>
   <soap:Body>
      <tem:Add>
         <tem:intA>45</tem:intA>
         <tem:intB>43</tem:intB>
      </tem:Add>
   </soap:Body>
</soap:Envelope>]]></con:request>
        <con:credentials>
          <con:authType>No Authorization</con:authType>
        </con:credentials>
        <con:jmsConfig JMSDeliveryMode="PERSISTENT"/>
        <con:jmsPropertyConfig/>
        <con:wsaConfig mustUnderstand="NONE" version="200508" action="http://tempuri.org/CalculatorSoap/AddRequest"/>
        <con:wsrmConfig version="1.2"/>
      </con:call>
    </con:operation>
    <con:operation id="c521bf63-e593-4269-9327-2ff5f74f39f3" isOneWay="false" action="http://tempuri.org/Divide" name="Divide" bindingOperationName="Divide" type="Request-Response" inputName="" receivesAttachments="false" sendsAttachments="false" anonymous="optional">
      <con:settings/>
      <con:call id="5118891b-771e-4ce1-a66e-a96c3997ea6b" name="Request 1">
        <con:settings>
          <con:setting id="com.eviware.soapui.impl.wsdl.WsdlRequest@request-headers">&lt;xml-fragment/></con:setting>
        </con:settings>
        <con:encoding>UTF-8</con:encoding>
        <con:endpoint>http://www.dneonline.com/calculator.asmx</con:endpoint>
        <con:request><![CDATA[<soap:Envelope xmlns:soap="http://www.w3.org/2003/05/soap-envelope" xmlns:tem="http://tempuri.org/">
   <soap:Header/>
   <soap:Body>
      <tem:Divide>
         <tem:intA>45</tem:intA>
         <tem:intB>32</tem:intB>
      </tem:Divide>
   </soap:Body>
</soap:Envelope>]]></con:request>
        <con:credentials>
          <con:authType>No Authorization</con:authType>
        </con:credentials>
        <con:jmsConfig JMSDeliveryMode="PERSISTENT"/>
        <con:jmsPropertyConfig/>
        <con:wsaConfig mustUnderstand="NONE" version="200508" action="http://tempuri.org/CalculatorSoap/DivideRequest"/>
        <con:wsrmConfig version="1.2"/>
      </con:call>
    </con:operation>
    <con:operation id="c0295714-5c2b-449f-a2b4-448777af0567" isOneWay="false" action="http://tempuri.org/Multiply" name="Multiply" bindingOperationName="Multiply" type="Request-Response" inputName="" receivesAttachments="false" sendsAttachments="false" anonymous="optional">
      <con:settings/>
      <con:call id="14dbd15d-eac0-44a2-9808-002c81c84d42" name="Request 1">
        <con:settings>
          <con:setting id="com.eviware.soapui.impl.wsdl.WsdlRequest@request-headers">&lt;xml-fragment/></con:setting>
        </con:settings>
        <con:encoding>UTF-8</con:encoding>
        <con:endpoint>http://www.dneonline.com/calculator.asmx</con:endpoint>
        <con:request><![CDATA[<soap:Envelope xmlns:soap="http://www.w3.org/2003/05/soap-envelope" xmlns:tem="http://tempuri.org/">
   <soap:Header/>
   <soap:Body>
      <tem:Multiply>
         <tem:intA>324</tem:intA>
         <tem:intB>54</tem:intB>
      </tem:Multiply>
   </soap:Body>
</soap:Envelope>]]></con:request>
        <con:credentials>
          <con:authType>No Authorization</con:authType>
        </con:credentials>
        <con:jmsConfig JMSDeliveryMode="PERSISTENT"/>
        <con:jmsPropertyConfig/>
        <con:wsaConfig mustUnderstand="NONE" version="200508" action="http://tempuri.org/CalculatorSoap/MultiplyRequest"/>
        <con:wsrmConfig version="1.2"/>
      </con:call>
    </con:operation>
    <con:operation id="9ebc9570-78a0-4e83-adc0-083e6be08220" isOneWay="false" action="http://tempuri.org/Subtract" name="Subtract" bindingOperationName="Subtract" type="Request-Response" inputName="" receivesAttachments="false" sendsAttachments="false" anonymous="optional">
      <con:settings/>
      <con:call id="193f164e-9dc4-4246-81a2-0867e1af687f" name="Request 1">
        <con:settings>
          <con:setting id="com.eviware.soapui.impl.wsdl.WsdlRequest@request-headers">&lt;xml-fragment/></con:setting>
        </con:settings>
        <con:encoding>UTF-8</con:encoding>
        <con:endpoint>http://www.dneonline.com/calculator.asmx</con:endpoint>
        <con:request><![CDATA[<soap:Envelope xmlns:soap="http://www.w3.org/2003/05/soap-envelope" xmlns:tem="http://tempuri.org/">
   <soap:Header/>
   <soap:Body>
      <tem:Subtract>
         <tem:intA>334</tem:intA>
         <tem:intB>22</tem:intB>
      </tem:Subtract>
   </soap:Body>
</soap:Envelope>]]></con:request>
        <con:credentials>
          <con:authType>No Authorization</con:authType>
        </con:credentials>
        <con:jmsConfig JMSDeliveryMode="PERSISTENT"/>
        <con:jmsPropertyConfig/>
        <con:wsaConfig mustUnderstand="NONE" version="200508" action="http://tempuri.org/CalculatorSoap/SubtractRequest"/>
        <con:wsrmConfig version="1.2"/>
      </con:call>
    </con:operation>
  </con:interface>
  <con:interface xsi:type="con:WsdlInterface" id="ff56a4cf-526a-469d-ad11-2c49e6ed89cc" wsaVersion="NONE" name="CalculatorSoap" type="wsdl" bindingName="{http://tempuri.org/}CalculatorSoap" soapVersion="1_1" anonymous="optional" definition="http://www.dneonline.com/calculator.asmx?WSDL"
    xmlns:xsi="http://www.w3.org/2001/XMLSchema-instance">
    <con:settings/>
    <con:definitionCache type="TEXT" rootPart="http://www.dneonline.com/calculator.asmx?WSDL">
      <con:part>
        <con:url>http://www.dneonline.com/calculator.asmx?WSDL</con:url>
        <con:content><![CDATA[<wsdl:definitions targetNamespace="http://tempuri.org/" xmlns:soap="http://schemas.xmlsoap.org/wsdl/soap/" xmlns:tm="http://microsoft.com/wsdl/mime/textMatching/" xmlns:soapenc="http://schemas.xmlsoap.org/soap/encoding/" xmlns:mime="http://schemas.xmlsoap.org/wsdl/mime/" xmlns:tns="http://tempuri.org/" xmlns:s="http://www.w3.org/2001/XMLSchema" xmlns:soap12="http://schemas.xmlsoap.org/wsdl/soap12/" xmlns:http="http://schemas.xmlsoap.org/wsdl/http/" xmlns:wsdl="http://schemas.xmlsoap.org/wsdl/">
  <wsdl:types>
    <s:schema elementFormDefault="qualified" targetNamespace="http://tempuri.org/">
      <s:element name="Add">
        <s:complexType>
          <s:sequence>
            <s:element minOccurs="1" maxOccurs="1" name="intA" type="s:int"/>
            <s:element minOccurs="1" maxOccurs="1" name="intB" type="s:int"/>
          </s:sequence>
        </s:complexType>
      </s:element>
      <s:element name="AddResponse">
        <s:complexType>
          <s:sequence>
            <s:element minOccurs="1" maxOccurs="1" name="AddResult" type="s:int"/>
          </s:sequence>
        </s:complexType>
      </s:element>
      <s:element name="Subtract">
        <s:complexType>
          <s:sequence>
            <s:element minOccurs="1" maxOccurs="1" name="intA" type="s:int"/>
            <s:element minOccurs="1" maxOccurs="1" name="intB" type="s:int"/>
          </s:sequence>
        </s:complexType>
      </s:element>
      <s:element name="SubtractResponse">
        <s:complexType>
          <s:sequence>
            <s:element minOccurs="1" maxOccurs="1" name="SubtractResult" type="s:int"/>
          </s:sequence>
        </s:complexType>
      </s:element>
      <s:element name="Multiply">
        <s:complexType>
          <s:sequence>
            <s:element minOccurs="1" maxOccurs="1" name="intA" type="s:int"/>
            <s:element minOccurs="1" maxOccurs="1" name="intB" type="s:int"/>
          </s:sequence>
        </s:complexType>
      </s:element>
      <s:element name="MultiplyResponse">
        <s:complexType>
          <s:sequence>
            <s:element minOccurs="1" maxOccurs="1" name="MultiplyResult" type="s:int"/>
          </s:sequence>
        </s:complexType>
      </s:element>
      <s:element name="Divide">
        <s:complexType>
          <s:sequence>
            <s:element minOccurs="1" maxOccurs="1" name="intA" type="s:int"/>
            <s:element minOccurs="1" maxOccurs="1" name="intB" type="s:int"/>
          </s:sequence>
        </s:complexType>
      </s:element>
      <s:element name="DivideResponse">
        <s:complexType>
          <s:sequence>
            <s:element minOccurs="1" maxOccurs="1" name="DivideResult" type="s:int"/>
          </s:sequence>
        </s:complexType>
      </s:element>
    </s:schema>
  </wsdl:types>
  <wsdl:message name="AddSoapIn">
    <wsdl:part name="parameters" element="tns:Add"/>
  </wsdl:message>
  <wsdl:message name="AddSoapOut">
    <wsdl:part name="parameters" element="tns:AddResponse"/>
  </wsdl:message>
  <wsdl:message name="SubtractSoapIn">
    <wsdl:part name="parameters" element="tns:Subtract"/>
  </wsdl:message>
  <wsdl:message name="SubtractSoapOut">
    <wsdl:part name="parameters" element="tns:SubtractResponse"/>
  </wsdl:message>
  <wsdl:message name="MultiplySoapIn">
    <wsdl:part name="parameters" element="tns:Multiply"/>
  </wsdl:message>
  <wsdl:message name="MultiplySoapOut">
    <wsdl:part name="parameters" element="tns:MultiplyResponse"/>
  </wsdl:message>
  <wsdl:message name="DivideSoapIn">
    <wsdl:part name="parameters" element="tns:Divide"/>
  </wsdl:message>
  <wsdl:message name="DivideSoapOut">
    <wsdl:part name="parameters" element="tns:DivideResponse"/>
  </wsdl:message>
  <wsdl:portType name="CalculatorSoap">
    <wsdl:operation name="Add">
      <wsdl:documentation>Adds two integers. This is a test WebService. ©DNE Online</wsdl:documentation>
      <wsdl:input message="tns:AddSoapIn"/>
      <wsdl:output message="tns:AddSoapOut"/>
    </wsdl:operation>
    <wsdl:operation name="Subtract">
      <wsdl:input message="tns:SubtractSoapIn"/>
      <wsdl:output message="tns:SubtractSoapOut"/>
    </wsdl:operation>
    <wsdl:operation name="Multiply">
      <wsdl:input message="tns:MultiplySoapIn"/>
      <wsdl:output message="tns:MultiplySoapOut"/>
    </wsdl:operation>
    <wsdl:operation name="Divide">
      <wsdl:input message="tns:DivideSoapIn"/>
      <wsdl:output message="tns:DivideSoapOut"/>
    </wsdl:operation>
  </wsdl:portType>
  <wsdl:binding name="CalculatorSoap" type="tns:CalculatorSoap">
    <soap:binding transport="http://schemas.xmlsoap.org/soap/http"/>
    <wsdl:operation name="Add">
      <soap:operation soapAction="http://tempuri.org/Add" style="document"/>
      <wsdl:input>
        <soap:body use="literal"/>
      </wsdl:input>
      <wsdl:output>
        <soap:body use="literal"/>
      </wsdl:output>
    </wsdl:operation>
    <wsdl:operation name="Subtract">
      <soap:operation soapAction="http://tempuri.org/Subtract" style="document"/>
      <wsdl:input>
        <soap:body use="literal"/>
      </wsdl:input>
      <wsdl:output>
        <soap:body use="literal"/>
      </wsdl:output>
    </wsdl:operation>
    <wsdl:operation name="Multiply">
      <soap:operation soapAction="http://tempuri.org/Multiply" style="document"/>
      <wsdl:input>
        <soap:body use="literal"/>
      </wsdl:input>
      <wsdl:output>
        <soap:body use="literal"/>
      </wsdl:output>
    </wsdl:operation>
    <wsdl:operation name="Divide">
      <soap:operation soapAction="http://tempuri.org/Divide" style="document"/>
      <wsdl:input>
        <soap:body use="literal"/>
      </wsdl:input>
      <wsdl:output>
        <soap:body use="literal"/>
      </wsdl:output>
    </wsdl:operation>
  </wsdl:binding>
  <wsdl:binding name="CalculatorSoap12" type="tns:CalculatorSoap">
    <soap12:binding transport="http://schemas.xmlsoap.org/soap/http"/>
    <wsdl:operation name="Add">
      <soap12:operation soapAction="http://tempuri.org/Add" style="document"/>
      <wsdl:input>
        <soap12:body use="literal"/>
      </wsdl:input>
      <wsdl:output>
        <soap12:body use="literal"/>
      </wsdl:output>
    </wsdl:operation>
    <wsdl:operation name="Subtract">
      <soap12:operation soapAction="http://tempuri.org/Subtract" style="document"/>
      <wsdl:input>
        <soap12:body use="literal"/>
      </wsdl:input>
      <wsdl:output>
        <soap12:body use="literal"/>
      </wsdl:output>
    </wsdl:operation>
    <wsdl:operation name="Multiply">
      <soap12:operation soapAction="http://tempuri.org/Multiply" style="document"/>
      <wsdl:input>
        <soap12:body use="literal"/>
      </wsdl:input>
      <wsdl:output>
        <soap12:body use="literal"/>
      </wsdl:output>
    </wsdl:operation>
    <wsdl:operation name="Divide">
      <soap12:operation soapAction="http://tempuri.org/Divide" style="document"/>
      <wsdl:input>
        <soap12:body use="literal"/>
      </wsdl:input>
      <wsdl:output>
        <soap12:body use="literal"/>
      </wsdl:output>
    </wsdl:operation>
  </wsdl:binding>
  <wsdl:service name="Calculator">
    <wsdl:port name="CalculatorSoap" binding="tns:CalculatorSoap">
      <soap:address location="http://www.dneonline.com/calculator.asmx"/>
    </wsdl:port>
    <wsdl:port name="CalculatorSoap12" binding="tns:CalculatorSoap12">
      <soap12:address location="http://www.dneonline.com/calculator.asmx"/>
    </wsdl:port>
  </wsdl:service>
</wsdl:definitions>]]></con:content>
        <con:type>http://schemas.xmlsoap.org/wsdl/</con:type>
      </con:part>
    </con:definitionCache>
    <con:endpoints>
      <con:endpoint>http://www.dneonline.com/calculator.asmx</con:endpoint>
    </con:endpoints>
    <con:operation id="fea04367-f121-413f-88e2-185f902d8fcc" isOneWay="false" action="http://tempuri.org/Add" name="Add" bindingOperationName="Add" type="Request-Response" inputName="" receivesAttachments="false" sendsAttachments="false" anonymous="optional">
      <con:settings/>
      <con:call id="f8f38228-8a7c-4eef-bf9a-70034241b67c" name="Request 1">
        <con:settings>
          <con:setting id="com.eviware.soapui.impl.wsdl.WsdlRequest@request-headers">&lt;xml-fragment/></con:setting>
        </con:settings>
        <con:encoding>UTF-8</con:encoding>
        <con:endpoint>http://www.dneonline.com/calculator.asmx</con:endpoint>
        <con:request><![CDATA[<soapenv:Envelope xmlns:soapenv="http://schemas.xmlsoap.org/soap/envelope/" xmlns:tem="http://tempuri.org/">
   <soapenv:Header/>
   <soapenv:Body>
      <tem:Add>
         <tem:intA>5</tem:intA>
         <tem:intB>40</tem:intB>
      </tem:Add>
   </soapenv:Body>
</soapenv:Envelope>
]]>        </con:request>
        <con:credentials>
          <con:authType>No Authorization</con:authType>
        </con:credentials>
        <con:jmsConfig JMSDeliveryMode="PERSISTENT"/>
        <con:jmsPropertyConfig/>
        <con:wsaConfig mustUnderstand="NONE" version="200508" action="http://tempuri.org/Add"/>
        <con:wsrmConfig version="1.2"/>
      </con:call>
    </con:operation>
    <con:operation id="b00fb00b-a865-4ca0-b5d5-57a621487051" isOneWay="false" action="http://tempuri.org/Divide" name="Divide" bindingOperationName="Divide" type="Request-Response" inputName="" receivesAttachments="false" sendsAttachments="false" anonymous="optional">
      <con:settings/>
      <con:call id="7ce3dd2a-3539-4659-a35c-65121cb190c2" name="Request 1">
        <con:settings>
          <con:setting id="com.eviware.soapui.impl.wsdl.WsdlRequest@request-headers">&lt;xml-fragment/></con:setting>
        </con:settings>
        <con:encoding>UTF-8</con:encoding>
        <con:endpoint>http://www.dneonline.com/calculator.asmx</con:endpoint>
        <con:request><![CDATA[<soapenv:Envelope xmlns:soapenv="http://schemas.xmlsoap.org/soap/envelope/" xmlns:tem="http://tempuri.org/">
   <soapenv:Header/>
   <soapenv:Body>
      <tem:Divide>
         <tem:intA>20</tem:intA>
         <tem:intB>2</tem:intB>
      </tem:Divide>
   </soapenv:Body>
</soapenv:Envelope>]]></con:request>
        <con:credentials>
          <con:authType>No Authorization</con:authType>
        </con:credentials>
        <con:jmsConfig JMSDeliveryMode="PERSISTENT"/>
        <con:jmsPropertyConfig/>
        <con:wsaConfig mustUnderstand="NONE" version="200508" action="http://tempuri.org/Divide"/>
        <con:wsrmConfig version="1.2"/>
      </con:call>
    </con:operation>
    <con:operation id="a2946013-eb90-4364-af8d-65e625d41c6f" isOneWay="false" action="http://tempuri.org/Multiply" name="Multiply" bindingOperationName="Multiply" type="Request-Response" inputName="" receivesAttachments="false" sendsAttachments="false" anonymous="optional">
      <con:settings/>
      <con:call id="1b3afbcb-699a-4a5d-a3b9-bd8242bb9da7" name="Request 1">
        <con:settings>
          <con:setting id="com.eviware.soapui.impl.wsdl.WsdlRequest@request-headers">&lt;xml-fragment/></con:setting>
        </con:settings>
        <con:encoding>UTF-8</con:encoding>
        <con:endpoint>http://www.dneonline.com/calculator.asmx</con:endpoint>
        <con:request><![CDATA[<soapenv:Envelope xmlns:soapenv="http://schemas.xmlsoap.org/soap/envelope/" xmlns:tem="http://tempuri.org/">
   <soapenv:Header/>
   <soapenv:Body>
      <tem:Multiply>
         <tem:intA>30</tem:intA>
         <tem:intB>23</tem:intB>
      </tem:Multiply>
   </soapenv:Body>
</soapenv:Envelope>]]></con:request>
        <con:credentials>
          <con:authType>No Authorization</con:authType>
        </con:credentials>
        <con:jmsConfig JMSDeliveryMode="PERSISTENT"/>
        <con:jmsPropertyConfig/>
        <con:wsaConfig mustUnderstand="NONE" version="200508" action="http://tempuri.org/Multiply"/>
        <con:wsrmConfig version="1.2"/>
      </con:call>
    </con:operation>
    <con:operation id="3f0d5ee0-354b-4ff5-b14e-4adbc92cd786" isOneWay="false" action="http://tempuri.org/Subtract" name="Subtract" bindingOperationName="Subtract" type="Request-Response" inputName="" receivesAttachments="false" sendsAttachments="false" anonymous="optional">
      <con:settings/>
      <con:call id="b7514d91-e22b-49f3-a02a-f18a0dba15b6" name="Request 1">
        <con:settings>
          <con:setting id="com.eviware.soapui.impl.wsdl.WsdlRequest@request-headers">&lt;xml-fragment/></con:setting>
        </con:settings>
        <con:encoding>UTF-8</con:encoding>
        <con:endpoint>http://www.dneonline.com/calculator.asmx</con:endpoint>
        <con:request><![CDATA[<soapenv:Envelope xmlns:soapenv="http://schemas.xmlsoap.org/soap/envelope/" xmlns:tem="http://tempuri.org/">
   <soapenv:Header/>
   <soapenv:Body>
      <tem:Subtract>
         <tem:intA>345</tem:intA>
         <tem:intB>100</tem:intB>
      </tem:Subtract>
   </soapenv:Body>
</soapenv:Envelope>]]></con:request>
        <con:credentials>
          <con:authType>No Authorization</con:authType>
        </con:credentials>
        <con:jmsConfig JMSDeliveryMode="PERSISTENT"/>
        <con:jmsPropertyConfig/>
        <con:wsaConfig mustUnderstand="NONE" version="200508" action="http://tempuri.org/Subtract"/>
        <con:wsrmConfig version="1.2"/>
      </con:call>
    </con:operation>
  </con:interface>
  <con:testSuite id="850434e9-574c-4bfb-8585-b3cce45da818" name="CalculatorSoap12 TestSuite">
    <con:settings/>
    <con:runType>SEQUENTIAL</con:runType>
    <con:testCase id="85129a9f-d77e-42cd-8b98-7623d0f6e758" failOnError="true" failTestCaseOnErrors="true" keepSession="false" maxResults="0" name="Add TestCase" searchProperties="true">
      <con:settings/>
      <con:testStep type="request" id="2ff08225-60af-4554-a033-c4c437d6f15c" name="Add">
        <con:settings/>
        <con:config xsi:type="con:RequestStep"
          xmlns:xsi="http://www.w3.org/2001/XMLSchema-instance">
          <con:interface>CalculatorSoap12</con:interface>
          <con:operation>Add</con:operation>
          <con:request name="Add" id="c19d83fc-8efb-463a-b03a-cece765dd5f6">
            <con:settings>
              <con:setting id="com.eviware.soapui.impl.wsdl.WsdlRequest@request-headers">&lt;xml-fragment/></con:setting>
            </con:settings>
            <con:encoding>UTF-8</con:encoding>
            <con:endpoint>http://www.dneonline.com/calculator.asmx</con:endpoint>
            <con:request><![CDATA[<soap:Envelope xmlns:soap="http://www.w3.org/2003/05/soap-envelope" xmlns:tem="http://tempuri.org/">
   <soap:Header/>
   <soap:Body>
      <tem:Add>
         <tem:intA>43</tem:intA>
         <tem:intB>21</tem:intB>
      </tem:Add>
   </soap:Body>
</soap:Envelope>]]></con:request>
            <con:credentials>
              <con:authType>No Authorization</con:authType>
            </con:credentials>
            <con:jmsConfig JMSDeliveryMode="PERSISTENT"/>
            <con:jmsPropertyConfig/>
            <con:wsaConfig action="http://tempuri.org/CalculatorSoap/AddRequest" mustUnderstand="NONE" version="200508"/>
            <con:wsrmConfig version="1.2"/>
          </con:request>
        </con:config>
      </con:testStep>
      <con:properties/>
    </con:testCase>
    <con:testCase id="4161b2ea-08d9-46f9-b2a2-33fbcfcf7a98" failOnError="true" failTestCaseOnErrors="true" keepSession="false" maxResults="0" name="Divide TestCase" searchProperties="true">
      <con:settings/>
      <con:testStep type="request" id="91645f11-a429-435e-9fe0-20894c9f9351" name="Divide">
        <con:settings/>
        <con:config xsi:type="con:RequestStep"
          xmlns:xsi="http://www.w3.org/2001/XMLSchema-instance">
          <con:interface>CalculatorSoap12</con:interface>
          <con:operation>Divide</con:operation>
          <con:request name="Divide" id="50e57d70-a02d-4f01-b69b-8656782ebc4f">
            <con:settings>
              <con:setting id="com.eviware.soapui.impl.wsdl.WsdlRequest@request-headers">&lt;xml-fragment/></con:setting>
            </con:settings>
            <con:encoding>UTF-8</con:encoding>
            <con:endpoint>http://www.dneonline.com/calculator.asmx</con:endpoint>
            <con:request><![CDATA[<soap:Envelope xmlns:soap="http://www.w3.org/2003/05/soap-envelope" xmlns:tem="http://tempuri.org/">
   <soap:Header/>
   <soap:Body>
      <tem:Divide>
         <tem:intA>32</tem:intA>
         <tem:intB>2</tem:intB>
      </tem:Divide>
   </soap:Body>
</soap:Envelope>]]></con:request>
            <con:credentials>
              <con:authType>No Authorization</con:authType>
            </con:credentials>
            <con:jmsConfig JMSDeliveryMode="PERSISTENT"/>
            <con:jmsPropertyConfig/>
            <con:wsaConfig action="http://tempuri.org/CalculatorSoap/DivideRequest" mustUnderstand="NONE" version="200508"/>
            <con:wsrmConfig version="1.2"/>
          </con:request>
        </con:config>
      </con:testStep>
      <con:properties/>
    </con:testCase>
    <con:testCase id="e73fd51e-8161-4de5-b906-36289493c5bd" failOnError="true" failTestCaseOnErrors="true" keepSession="false" maxResults="0" name="Multiply TestCase" searchProperties="true">
      <con:settings/>
      <con:testStep type="request" id="9c87aebd-8444-4af1-9192-8063740d9869" name="Multiply">
        <con:settings/>
        <con:config xsi:type="con:RequestStep"
          xmlns:xsi="http://www.w3.org/2001/XMLSchema-instance">
          <con:interface>CalculatorSoap12</con:interface>
          <con:operation>Multiply</con:operation>
          <con:request name="Multiply" id="1dcccd51-cad4-4161-af3c-c22a21301889">
            <con:settings>
              <con:setting id="com.eviware.soapui.impl.wsdl.WsdlRequest@request-headers">&lt;xml-fragment/></con:setting>
            </con:settings>
            <con:encoding>UTF-8</con:encoding>
            <con:endpoint>http://www.dneonline.com/calculator.asmx</con:endpoint>
            <con:request><![CDATA[<soap:Envelope xmlns:soap="http://www.w3.org/2003/05/soap-envelope" xmlns:tem="http://tempuri.org/">
   <soap:Header/>
   <soap:Body>
      <tem:Multiply>
         <tem:intA>33</tem:intA>
         <tem:intB>4</tem:intB>
      </tem:Multiply>
   </soap:Body>
</soap:Envelope>]]></con:request>
            <con:credentials>
              <con:authType>No Authorization</con:authType>
            </con:credentials>
            <con:jmsConfig JMSDeliveryMode="PERSISTENT"/>
            <con:jmsPropertyConfig/>
            <con:wsaConfig action="http://tempuri.org/CalculatorSoap/MultiplyRequest" mustUnderstand="NONE" version="200508"/>
            <con:wsrmConfig version="1.2"/>
          </con:request>
        </con:config>
      </con:testStep>
      <con:properties/>
    </con:testCase>
    <con:testCase id="fbf76b22-18be-4d4e-a7d5-91ec10a8185d" failOnError="true" failTestCaseOnErrors="true" keepSession="false" maxResults="0" name="Subtract TestCase" searchProperties="true">
      <con:settings/>
      <con:testStep type="request" id="b340a98a-eeb6-4c80-b958-48c4194c61b1" name="Subtract">
        <con:settings/>
        <con:config xsi:type="con:RequestStep"
          xmlns:xsi="http://www.w3.org/2001/XMLSchema-instance">
          <con:interface>CalculatorSoap12</con:interface>
          <con:operation>Subtract</con:operation>
          <con:request name="Subtract" id="457780b1-5374-4b50-b1b4-d54c109bb8e2">
            <con:settings>
              <con:setting id="com.eviware.soapui.impl.wsdl.WsdlRequest@request-headers">&lt;xml-fragment/></con:setting>
            </con:settings>
            <con:encoding>UTF-8</con:encoding>
            <con:endpoint>http://www.dneonline.com/calculator.asmx</con:endpoint>
            <con:request><![CDATA[<soap:Envelope xmlns:soap="http://www.w3.org/2003/05/soap-envelope" xmlns:tem="http://tempuri.org/">
   <soap:Header/>
   <soap:Body>
      <tem:Subtract>
         <tem:intA>21</tem:intA>
         <tem:intB>5</tem:intB>
      </tem:Subtract>
   </soap:Body>
</soap:Envelope>]]></con:request>
            <con:credentials>
              <con:authType>No Authorization</con:authType>
            </con:credentials>
            <con:jmsConfig JMSDeliveryMode="PERSISTENT"/>
            <con:jmsPropertyConfig/>
            <con:wsaConfig action="http://tempuri.org/CalculatorSoap/SubtractRequest" mustUnderstand="NONE" version="200508"/>
            <con:wsrmConfig version="1.2"/>
          </con:request>
        </con:config>
      </con:testStep>
      <con:properties/>
    </con:testCase>
    <con:properties/>
  </con:testSuite>
  <con:testSuite id="ee30c2f4-b9a9-4f92-9e5d-bd5af50005d7" name="CalculatorSoap TestSuite">
    <con:settings/>
    <con:runType>SEQUENTIAL</con:runType>
    <con:testCase id="17850f78-84f7-44ca-a8c5-38d25c76c027" failOnError="true" failTestCaseOnErrors="true" keepSession="false" maxResults="0" name="Add TestCase" searchProperties="true">
      <con:settings/>
      <con:testStep type="request" id="4519286b-4362-4ab6-9da0-fe500845f7c3" name="Add">
        <con:settings/>
        <con:config xsi:type="con:RequestStep"
          xmlns:xsi="http://www.w3.org/2001/XMLSchema-instance">
          <con:interface>CalculatorSoap</con:interface>
          <con:operation>Add</con:operation>
          <con:request name="Add" id="89cf93b8-151a-4ed4-919e-46eac5f1e1a4">
            <con:settings>
              <con:setting id="com.eviware.soapui.impl.wsdl.WsdlRequest@request-headers">&lt;xml-fragment/></con:setting>
            </con:settings>
            <con:encoding>UTF-8</con:encoding>
            <con:endpoint>http://www.dneonline.com/calculator.asmx</con:endpoint>
            <con:request><![CDATA[<soapenv:Envelope xmlns:soapenv="http://schemas.xmlsoap.org/soap/envelope/" xmlns:tem="http://tempuri.org/">
   <soapenv:Header/>
   <soapenv:Body>
      <tem:Add>
         <tem:intA>32</tem:intA>
         <tem:intB>54</tem:intB>
      </tem:Add>
   </soapenv:Body>
</soapenv:Envelope>]]></con:request>
            <con:credentials>
              <con:authType>No Authorization</con:authType>
            </con:credentials>
            <con:jmsConfig JMSDeliveryMode="PERSISTENT"/>
            <con:jmsPropertyConfig/>
            <con:wsaConfig action="http://tempuri.org/Add" mustUnderstand="NONE" version="200508"/>
            <con:wsrmConfig version="1.2"/>
          </con:request>
        </con:config>
      </con:testStep>
      <con:properties/>
    </con:testCase>
    <con:testCase id="6ace8ecc-fde5-4ed2-bf32-f24b35a2676a" failOnError="true" failTestCaseOnErrors="true" keepSession="false" maxResults="0" name="Divide TestCase" searchProperties="true">
      <con:settings/>
      <con:testStep type="request" id="2d453df4-4205-45aa-8838-2f7bce6a9614" name="Divide">
        <con:settings/>
        <con:config xsi:type="con:RequestStep"
          xmlns:xsi="http://www.w3.org/2001/XMLSchema-instance">
          <con:interface>CalculatorSoap</con:interface>
          <con:operation>Divide</con:operation>
          <con:request name="Divide" id="f7efeb3d-0f34-4dd1-9fa1-07ab012e9d50">
            <con:settings>
              <con:setting id="com.eviware.soapui.impl.wsdl.WsdlRequest@request-headers">&lt;xml-fragment/></con:setting>
            </con:settings>
            <con:encoding>UTF-8</con:encoding>
            <con:endpoint>http://www.dneonline.com/calculator.asmx</con:endpoint>
            <con:request><![CDATA[<soapenv:Envelope xmlns:soapenv="http://schemas.xmlsoap.org/soap/envelope/" xmlns:tem="http://tempuri.org/">
   <soapenv:Header/>
   <soapenv:Body>
      <tem:Divide>
         <tem:intA>65</tem:intA>
         <tem:intB>32</tem:intB>
      </tem:Divide>
   </soapenv:Body>
</soapenv:Envelope>]]></con:request>
            <con:credentials>
              <con:authType>No Authorization</con:authType>
            </con:credentials>
            <con:jmsConfig JMSDeliveryMode="PERSISTENT"/>
            <con:jmsPropertyConfig/>
            <con:wsaConfig action="http://tempuri.org/Divide" mustUnderstand="NONE" version="200508"/>
            <con:wsrmConfig version="1.2"/>
          </con:request>
        </con:config>
      </con:testStep>
      <con:properties/>
    </con:testCase>
    <con:testCase id="761f3e66-c2fe-43d1-880a-5e2c529e20e8" failOnError="true" failTestCaseOnErrors="true" keepSession="false" maxResults="0" name="Multiply TestCase" searchProperties="true">
      <con:settings/>
      <con:testStep type="request" id="c4ee7f76-b06f-43b2-ac11-613f7a12e2cc" name="Multiply">
        <con:settings/>
        <con:config xsi:type="con:RequestStep"
          xmlns:xsi="http://www.w3.org/2001/XMLSchema-instance">
          <con:interface>CalculatorSoap</con:interface>
          <con:operation>Multiply</con:operation>
          <con:request name="Multiply" id="67132992-0d9c-47da-a996-0ecaac466b0b">
            <con:settings>
              <con:setting id="com.eviware.soapui.impl.wsdl.WsdlRequest@request-headers">&lt;xml-fragment/></con:setting>
            </con:settings>
            <con:encoding>UTF-8</con:encoding>
            <con:endpoint>http://www.dneonline.com/calculator.asmx</con:endpoint>
            <con:request><![CDATA[<soap:Envelope xmlns:soap="http://www.w3.org/2003/05/soap-envelope" xmlns:tem="http://tempuri.org/">
   <soap:Header/>
   <soap:Body>
      <tem:Multiply>
         <tem:intA>33</tem:intA>
         <tem:intB>4</tem:intB>
      </tem:Multiply>
   </soap:Body>
</soap:Envelope>]]></con:request>
            <con:credentials>
              <con:authType>No Authorization</con:authType>
            </con:credentials>
            <con:jmsConfig JMSDeliveryMode="PERSISTENT"/>
            <con:jmsPropertyConfig/>
            <con:wsaConfig action="http://tempuri.org/Multiply" mustUnderstand="NONE" version="200508"/>
            <con:wsrmConfig version="1.2"/>
          </con:request>
        </con:config>
      </con:testStep>
      <con:properties/>
    </con:testCase>
    <con:testCase id="4ae48991-04bc-4703-964c-a63e3c72be03" failOnError="true" failTestCaseOnErrors="true" keepSession="false" maxResults="0" name="Subtract TestCase" searchProperties="true">
      <con:settings/>
      <con:testStep type="request" id="81010f76-57d3-49cd-be2d-2883003c0bac" name="Subtract">
        <con:settings/>
        <con:config xsi:type="con:RequestStep"
          xmlns:xsi="http://www.w3.org/2001/XMLSchema-instance">
          <con:interface>CalculatorSoap</con:interface>
          <con:operation>Subtract</con:operation>
          <con:request name="Subtract" id="da1932a1-9248-49a6-b9bf-22b0a82f18c5">
            <con:settings>
              <con:setting id="com.eviware.soapui.impl.wsdl.WsdlRequest@request-headers">&lt;xml-fragment/></con:setting>
            </con:settings>
            <con:encoding>UTF-8</con:encoding>
            <con:endpoint>http://www.dneonline.com/calculator.asmx</con:endpoint>
            <con:request><![CDATA[<soapenv:Envelope xmlns:soapenv="http://schemas.xmlsoap.org/soap/envelope/" xmlns:tem="http://tempuri.org/">
   <soapenv:Header/>
   <soapenv:Body>
      <tem:Subtract>
         <tem:intA>4</tem:intA>
         <tem:intB>2</tem:intB>
      </tem:Subtract>
   </soapenv:Body>
</soapenv:Envelope>]]></con:request>
            <con:credentials>
              <con:authType>No Authorization</con:authType>
            </con:credentials>
            <con:jmsConfig JMSDeliveryMode="PERSISTENT"/>
            <con:jmsPropertyConfig/>
            <con:wsaConfig action="http://tempuri.org/Subtract" mustUnderstand="NONE" version="200508"/>
            <con:wsrmConfig version="1.2"/>
          </con:request>
        </con:config>
      </con:testStep>
      <con:properties/>
    </con:testCase>
    <con:properties/>
  </con:testSuite>
  <con:properties/>
  <con:wssContainer/>
  <con:oAuth2ProfileContainer/>
  <con:oAuth1ProfileContainer/>
</con:soapui-project>